dfgraph/__init__.py
dfgraph/database.py
dfgraph/graph.py
dfgraph/seralizer.py
dfgraph-0.1.3.dist-info/LICENSE
dfgraph-0.1.3.dist-info/METADATA
dfgraph-0.1.3.dist-info/WHEEL
dfgraph-0.1.3.dist-info/top_level.txt
dfgraph-0.1.3.dist-info/RECORD
